pynche/__init__.py
pynche/chipviewer.py
pynche/colordb.py
pynche/detailsviewer.py
pynche/listviewer.py
pynche/main.py
pynche/stripviewer.py
pynche/switchboard.py
pynche/textviewer.py
pynche/typeinviewer.py
pynche/widget.py
pynche/data/__init__.py
pynche/data/html40colors.txt
pynche/data/namedcolors.txt
pynche/data/rgb.txt
pynche/data/webcolors.txt
pynche/data/websafe.txt
pynche/data/xlicense.txt
pynche-3.0.dist-info/METADATA
pynche-3.0.dist-info/WHEEL
pynche-3.0.dist-info/entry_points.txt
pynche-3.0.dist-info/licenses/LICENSE
pynche-3.0.dist-info/RECORD
