Metadata-Version: 2.4
Name: pynche
Version: 3.0
Summary: The Pythonically Natural Color and Hue Editor
Project-URL: Home Page, https://gitlab.com/warsaw/pynche/-/blob/main/README.md
Project-URL: Documentation, https://gitlab.com/warsaw/pynche/-/blob/main/README.md
Project-URL: Source, https://gitlab.com/warsaw/pynche.git
Project-URL: Bug Tracker, https://gitlab.com/warsaw/pynche/-/issues
Author-email: Barry Warsaw <barry@python.org>
License: Apache-2.0
License-File: LICENSE
Keywords: color chooser,tkinter
Classifier: Development Status :: 5 - Production/Stable
Classifier: Development Status :: 6 - Mature
Classifier: Environment :: X11 Applications
Classifier: Intended Audience :: End Users/Desktop
Classifier: License :: OSI Approved :: Apache Software License
Classifier: Operating System :: MacOS :: MacOS X
Classifier: Operating System :: Microsoft :: Windows
Classifier: Operating System :: POSIX
Classifier: Programming Language :: Python
Classifier: Programming Language :: Python :: 3
Classifier: Topic :: Desktop Environment
Requires-Python: >=3.10
Requires-Dist: atpublic
